{
  "version": "4.2.0",
  "updated": "2026-04-09T00:00:00Z",
  "total": 5,
  "workAreas": [
    {
      "id": "frontend",
      "title": "Frontend",
      "description": "Interfaces, design systems, browser work, and product polish."
    },
    {
      "id": "backend",
      "title": "Backend",
      "description": "Systems, data, security, and runtime operations."
    },
    {
      "id": "mobile",
      "title": "Mobile",
      "description": "Native apps, React Native, device testing, and mobile delivery."
    },
    {
      "id": "workflow",
      "title": "Workflow",
      "description": "Files, docs, planning, and release work."
    },
    {
      "id": "agent-engineering",
      "title": "Agent Engineering",
      "description": "Prompts, tools, evaluation, orchestration, and agent runtime design."
    }
  ],
  "collections": [
    {
      "id": "starter-pack",
      "title": "Starter Pack",
      "description": "Recommended first install for Bash framework maintenance with tests, linting, and performance checks.",
      "skillCount": 0,
      "installedCount": 0,
      "startHere": [],
      "skills": [
        "bash-bats-loop",
        "hyperfine-benchmark-loop",
        "shellcheck-triage",
        "coverage-gap-planner",
        "bash-maintenance-orchestrator"
      ]
    }
  ],
  "skills": [
    {
      "name": "coverage-gap-planner",
      "description": "Use when Bash maintenance work needs a deliberate plan for which untested behaviors to cover next, especially after failures or shared-module edits.",
      "category": "development",
      "workArea": "workflow",
      "branch": "Bash / Coverage",
      "author": "unknown",
      "source": "/home/chous/github/rydnr/dry-wit/dry-wit-ops/coverage-gap-planner",
      "license": "MIT",
      "path": "skills/coverage-gap-planner",
      "tier": "house",
      "distribution": "bundled",
      "vendored": true,
      "installSource": "",
      "tags": [],
      "featured": true,
      "verified": false,
      "origin": "curated",
      "trust": "listed",
      "syncMode": "snapshot",
      "sourceUrl": "",
      "whyHere": "Keeps the workflow shelf focused on high-yield Bash coverage gaps instead of broad low-value test expansion.",
      "addedDate": "2026-04-09",
      "lastVerified": "",
      "notes": "",
      "labels": [],
      "collections": "",
      "lastCurated": "2026-04-09T00:00:00Z",
      "requires": []
    },
    {
      "name": "bash-bats-loop",
      "description": "Use when maintaining Bash code and the next move should be a fast Bats regression loop that narrows failures before editing more code.",
      "category": "development",
      "workArea": "workflow",
      "branch": "Bash / Test Loops",
      "author": "unknown",
      "source": "/home/chous/github/rydnr/dry-wit/dry-wit-ops/bash-bats-loop",
      "license": "MIT",
      "path": "skills/bash-bats-loop",
      "tier": "house",
      "distribution": "bundled",
      "vendored": true,
      "installSource": "",
      "tags": [],
      "featured": true,
      "verified": false,
      "origin": "curated",
      "trust": "listed",
      "syncMode": "snapshot",
      "sourceUrl": "",
      "whyHere": "Anchors the workflow shelf with a concrete Bats-driven regression loop for Bash framework maintenance and fast confidence after edits.",
      "addedDate": "2026-04-09",
      "lastVerified": "",
      "notes": "",
      "labels": [],
      "collections": "",
      "lastCurated": "2026-04-09T00:00:00Z",
      "requires": []
    },
    {
      "name": "shellcheck-triage",
      "description": "Use when Bash maintenance work should be driven by ShellCheck findings, especially when warnings need prioritization and safe fixes.",
      "category": "development",
      "workArea": "workflow",
      "branch": "Bash / Linting",
      "author": "unknown",
      "source": "/home/chous/github/rydnr/dry-wit/dry-wit-ops/shellcheck-triage",
      "license": "MIT",
      "path": "skills/shellcheck-triage",
      "tier": "house",
      "distribution": "bundled",
      "vendored": true,
      "installSource": "",
      "tags": [],
      "featured": false,
      "verified": false,
      "origin": "curated",
      "trust": "listed",
      "syncMode": "snapshot",
      "sourceUrl": "",
      "whyHere": "Adds a lint-first Bash triage path so warning cleanup is prioritized by behavior risk rather than bulk suppression.",
      "addedDate": "2026-04-09",
      "lastVerified": "",
      "notes": "",
      "labels": [],
      "collections": "",
      "lastCurated": "2026-04-09T00:00:00Z",
      "requires": []
    },
    {
      "name": "hyperfine-benchmark-loop",
      "description": "Use when Bash performance work should be measured with repeatable hyperfine benchmarks instead of intuition or one-off timing.",
      "category": "development",
      "workArea": "backend",
      "branch": "Bash / Performance",
      "author": "unknown",
      "source": "/home/chous/github/rydnr/dry-wit/dry-wit-ops/hyperfine-benchmark-loop",
      "license": "MIT",
      "path": "skills/hyperfine-benchmark-loop",
      "tier": "house",
      "distribution": "bundled",
      "vendored": true,
      "installSource": "",
      "tags": [],
      "featured": true,
      "verified": false,
      "origin": "curated",
      "trust": "listed",
      "syncMode": "snapshot",
      "sourceUrl": "",
      "whyHere": "Gives the backend shelf an evidence-based hyperfine loop for Bash runtime tuning and regression checks.",
      "addedDate": "2026-04-09",
      "lastVerified": "",
      "notes": "",
      "labels": [],
      "collections": "",
      "lastCurated": "2026-04-09T00:00:00Z",
      "requires": []
    },
    {
      "name": "bash-maintenance-orchestrator",
      "description": "Use when a Bash maintenance task needs coordinated testing, linting, and benchmarking instead of treating those loops as separate afterthoughts.",
      "category": "development",
      "workArea": "backend",
      "branch": "Bash / Maintenance",
      "author": "unknown",
      "source": "/home/chous/github/rydnr/dry-wit/dry-wit-ops/bash-maintenance-orchestrator",
      "license": "MIT",
      "path": "skills/bash-maintenance-orchestrator",
      "tier": "house",
      "distribution": "bundled",
      "vendored": true,
      "installSource": "",
      "tags": [],
      "featured": true,
      "verified": false,
      "origin": "curated",
      "trust": "listed",
      "syncMode": "snapshot",
      "sourceUrl": "",
      "whyHere": "Provides the cross-loop execution order for Bash maintenance tasks where tests, linting, and performance checks must be coordinated deliberately.",
      "addedDate": "2026-04-09",
      "lastVerified": "",
      "notes": "",
      "labels": [],
      "collections": "",
      "lastCurated": "2026-04-09T00:00:00Z",
      "requires": []
    }
  ],
  "libraryName": "dry-wit-ops",
  "librarySlug": "dry-wit-ops"
}
